MANIFEST.in
README.rst
VERSION
kon.py
pylintrc
setup.cfg
setup.py
test_kon.py
tox.ini
kon.egg-info/PKG-INFO
kon.egg-info/SOURCES.txt
kon.egg-info/dependency_links.txt
kon.egg-info/not-zip-safe
kon.egg-info/requires.txt
kon.egg-info/top_level.txt