Metadata-Version: 1.1
Name: kon
Version: 0.0.1
Summary: A configuration file(s) management library
Home-page: https://bitbucket.org/wampeter/kon
Author: Wampeter Foma
Author-email: foma@wampeter.org
License: GNU GPL v3
Platform: any
Classifier: Intended Audience :: Developers
Classifier: License :: OSI Approved :: GNU General Public License v3 (GPLv3)
Classifier: Operating System :: OS Independent
Classifier: Programming Language :: Python
Classifier: Topic :: Software Development :: Libraries
Classifier: Topic :: Software Development :: Libraries :: Python Modules
